__init__.py
raglight/__init__.py
raglight/cli/__init__.py
raglight/cli/main.py
raglight/cli/nltk_management.py
raglight/config/__init__.py
raglight/config/agentic_rag_config.py
raglight/config/rag_config.py
raglight/config/rat_config.py
raglight/config/settings.py
raglight/config/vector_store_config.py
raglight/cross_encoder/__init__.py
raglight/cross_encoder/cross_encoder_model.py
raglight/cross_encoder/huggingface_cross_encoder.py
raglight/document_processing/__init__.py
raglight/document_processing/code_processor.py
raglight/document_processing/document_processor.py
raglight/document_processing/document_processor_factory.py
raglight/document_processing/pdf_processor.py
raglight/document_processing/text_processor.py
raglight/document_processing/vlm_pdf_processor.py
raglight/embeddings/__init__.py
raglight/embeddings/embeddings_model.py
raglight/embeddings/gemini_embeddings.py
raglight/embeddings/huggingface_embeddings.py
raglight/embeddings/ollama_embeddings.py
raglight/embeddings/openai_embeddings.py
raglight/llm/__init__.py
raglight/llm/gemini_model.py
raglight/llm/llm.py
raglight/llm/lmstudio_model.py
raglight/llm/mistral_model.py
raglight/llm/ollama_model.py
raglight/llm/openai_model.py
raglight/models/__init__.py
raglight/models/data_source_model.py
raglight/rag/__init__.py
raglight/rag/agentic_rag.py
raglight/rag/builder.py
raglight/rag/rag.py
raglight/rag/simple_agentic_rag_api.py
raglight/rag/simple_rag_api.py
raglight/rat/__init__.py
raglight/rat/rat.py
raglight/rat/simple_rat_api.py
raglight/scrapper/__init__.py
raglight/scrapper/github_scrapper.py
raglight/vectorstore/__init__.py
raglight/vectorstore/chroma.py
raglight/vectorstore/vector_store.py
raglight-2.8.1.dist-info/licenses/LICENSE
raglight-2.8.1.dist-info/METADATA
raglight-2.8.1.dist-info/WHEEL
raglight-2.8.1.dist-info/entry_points.txt
raglight-2.8.1.dist-info/top_level.txt
raglight-2.8.1.dist-info/RECORD
