Metadata-Version: 2.4
Name: raglight
Version: 2.8.1
Summary: RAGLight is a lightweight and modular Python library for implementing Retrieval-Augmented Generation (RAG). It enhances the capabilities of Large Language Models (LLMs) by combining document retrieval with natural language inference.
Author-email: Bessouat40 <roman.bessouat@orange.fr>
License: MIT License
Requires-Python: >=3.11
License-File: LICENSE
Requires-Dist: langchain-ollama==0.2.1
Requires-Dist: langchain-openai==0.2.0
Requires-Dist: langchain==0.3.11
Requires-Dist: mistralai==1.5.0
Requires-Dist: smolagents[mcp]==1.21.1
Requires-Dist: langchain-huggingface==0.1.2
Requires-Dist: langchain-text-splitters==0.3.2
Requires-Dist: ollama==0.4.0
Requires-Dist: unstructured[all-docs]==0.16.11
Requires-Dist: langchain-core==0.3.24
Requires-Dist: typing==3.7.4.3
Requires-Dist: typing-extensions==4.12.2
Requires-Dist: langgraph==0.2.59
Requires-Dist: langchain-chroma==0.1.4
Requires-Dist: langchain-community==0.3.11
Requires-Dist: litellm==1.52.16
Requires-Dist: typer==0.16.0
Requires-Dist: rich==14.0.0
Requires-Dist: quo==2023.5.1
Requires-Dist: questionary==2.0.1
Requires-Dist: langchain-google-genai==2.0.7
Requires-Dist: python-dotenv>=1.1.1
Requires-Dist: pydantic>=2.11.7
Requires-Dist: google-genai>=1.2.0
Dynamic: license-file
